service/handler/chunk_handler.py
service/handler/embedding_handler.py
service/handler/pdf_handler.py
utils/analyze.py
utils/estimate_dpi_helper.py
utils/is_gibberish.py
utils/llm_connection.py
docling_demo-0.1.1.dist-info/METADATA
docling_demo-0.1.1.dist-info/WHEEL
docling_demo-0.1.1.dist-info/top_level.txt
docling_demo-0.1.1.dist-info/RECORD
