Metadata-Version: 2.4
Name: docling_demo
Version: 0.1.1
Summary: Add your description here
Requires-Python: >=3.10
Requires-Dist: azure-identity>=1.25.1
Requires-Dist: azure-search>=1.0.0b2
Requires-Dist: azure-search-documents>=11.6.0
Requires-Dist: build>=1.3.0
Requires-Dist: docling>=2.64.0
Requires-Dist: hf-xet>=1.2.0
Requires-Dist: langchain>=1.1.2
Requires-Dist: langchain-docling>=2.0.0
Requires-Dist: langchain-openai>=1.1.0
Requires-Dist: onnxruntime>=1.23.2
Requires-Dist: pymupdf>=1.26.6
Requires-Dist: transformers>=4.57.3
Requires-Dist: twine>=6.2.0
